odoo/addons/sale_input_barcode/README.rst
odoo/addons/sale_input_barcode/__init__.py
odoo/addons/sale_input_barcode/__manifest__.py
odoo/addons/sale_input_barcode/i18n/fr_FR.po
odoo/addons/sale_input_barcode/i18n/it.po
odoo/addons/sale_input_barcode/i18n/sale_input_barcode.pot
odoo/addons/sale_input_barcode/models/__init__.py
odoo/addons/sale_input_barcode/models/product_barcode_line_mixin.py
odoo/addons/sale_input_barcode/models/res_config_settings.py
odoo/addons/sale_input_barcode/models/sale_order.py
odoo/addons/sale_input_barcode/readme/CONFIGURE.rst
odoo/addons/sale_input_barcode/readme/CONTIBUTORS.rst
odoo/addons/sale_input_barcode/readme/DESCRIPTION.rst
odoo/addons/sale_input_barcode/readme/USAGE.rst
odoo/addons/sale_input_barcode/static/description/icon.png
odoo/addons/sale_input_barcode/static/description/index.html
odoo/addons/sale_input_barcode/tests/__init__.py
odoo/addons/sale_input_barcode/tests/test_sale_input_barcode.py
odoo/addons/sale_input_barcode/views/sale.xml
odoo/addons/sale_input_barcode/views/sale_input_settings_view.xml
odoo14_addon_sale_input_barcode-14.0.2.1.0.dist-info/METADATA
odoo14_addon_sale_input_barcode-14.0.2.1.0.dist-info/WHEEL
odoo14_addon_sale_input_barcode-14.0.2.1.0.dist-info/top_level.txt
odoo14_addon_sale_input_barcode-14.0.2.1.0.dist-info/RECORD
