Metadata-Version: 2.1
Name: odoo14-addon-sale_input_barcode
Version: 14.0.2.1.0
Summary: Add Sale line with barcode
Home-page: https://github.com/OCA/stock-logistics-barcode
Author: Akretion, Odoo Community Association (OCA)
Author-email: support@odoo-community.org
License: AGPL-3
Classifier: Programming Language :: Python
Classifier: Framework :: Odoo
Classifier: Framework :: Odoo :: 14.0
Classifier: License :: OSI Approved :: GNU Affero General Public License v3
Requires-Python: >=3.6
Requires-Dist: odoo14-addon-barcode-action
Requires-Dist: odoo<14.1dev,>=14.0a
